{
  "$schema": "https://ui.shadcn.com/schema/registry-item.json",
  "name": "form",
  "description": "A complete form block with multiple input types.",
  "registryDependencies": [
    "@loveui/form"
  ],
  "files": [
    {
      "path": "registry/default/examples/form.tsx",
      "content": "\"use client\"\n\nimport { useState, type FormEventHandler } from \"react\"\nimport {\n  CalendarIcon,\n  ImageIcon,\n  InfoIcon,\n  MapPinIcon,\n  TagIcon,\n  UsersIcon,\n} from \"lucide-react\"\nimport { toast } from \"sonner\"\n\nimport {\n  Choicebox,\n  ChoiceboxIndicator,\n  ChoiceboxItem,\n  ChoiceboxItemDescription,\n  ChoiceboxItemHeader,\n  ChoiceboxItemTitle,\n} from \"../../../../../packages/choicebox\"\nimport {\n  Combobox,\n  ComboboxContent,\n  ComboboxEmpty,\n  ComboboxGroup,\n  ComboboxInput,\n  ComboboxItem,\n  ComboboxList,\n  ComboboxTrigger,\n} from \"../../../../../packages/combobox\"\nimport {\n  Dropzone,\n  DropzoneContent,\n  DropzoneEmptyState,\n} from \"../../../../../packages/dropzone\"\nimport {\n  MiniCalendar,\n  MiniCalendarDay,\n  MiniCalendarDays,\n  MiniCalendarNavigation,\n} from \"../../../../../packages/mini-calendar\"\nimport {\n  Tags,\n  TagsContent,\n  TagsEmpty,\n  TagsGroup,\n  TagsInput,\n  TagsItem,\n  TagsList,\n  TagsTrigger,\n  TagsValue,\n} from \"../../../../../packages/tags\"\nimport { Button } from \"../../../../../packages/ui/src/ui/button\"\nimport { Input } from \"../../../../../packages/ui/src/ui/input\"\nimport { Label } from \"../../../../../packages/ui/src/ui/label\"\nimport { Textarea } from \"../../../../../packages/ui/src/ui/textarea\"\n\nconst eventTypes = [\n  {\n    value: \"conference\",\n    label: \"Conference\",\n    description: \"Professional gathering with speakers and networking\",\n  },\n  {\n    value: \"workshop\",\n    label: \"Workshop\",\n    description: \"Hands-on learning experience with practical activities\",\n  },\n  {\n    value: \"meetup\",\n    label: \"Meetup\",\n    description: \"Casual gathering for like-minded individuals\",\n  },\n  {\n    value: \"webinar\",\n    label: \"Webinar\",\n    description: \"Online presentation or seminar via video conference\",\n  },\n]\n\nconst venues = [\n  { value: \"convention-center\", label: \"Downtown Convention Center\" },\n  { value: \"hotel-ballroom\", label: \"Grand Hotel Ballroom\" },\n  { value: \"university-hall\", label: \"University Main Hall\" },\n  { value: \"co-working-space\", label: \"Tech Hub Co-working Space\" },\n  { value: \"online\", label: \"Online/Virtual\" },\n]\n\nconst availableTags = [\n  \"Technology\",\n  \"Business\",\n  \"Marketing\",\n  \"Design\",\n  \"Development\",\n  \"AI/ML\",\n  \"Startup\",\n  \"Networking\",\n  \"Education\",\n  \"Innovation\",\n  \"Remote Work\",\n  \"Leadership\",\n]\n\nconst Example = () => {\n  const [eventType, setEventType] = useState(\"\")\n  const [venue, setVenue] = useState(\"\")\n  const [selectedDate, setSelectedDate] = useState<Date | undefined>()\n  const [files, setFiles] = useState<File[]>([])\n  const [selectedTags, setSelectedTags] = useState<string[]>([])\n\n  const handleTagSelect = (tag: string) => {\n    if (!selectedTags.includes(tag)) {\n      setSelectedTags([...selectedTags, tag])\n    }\n  }\n\n  const handleTagRemove = (tagToRemove: string) => {\n    setSelectedTags(selectedTags.filter((tag) => tag !== tagToRemove))\n  }\n\n  const handleSubmit: FormEventHandler<HTMLFormElement> = (event) => {\n    event.preventDefault()\n\n    toast.success(\"Event created successfully\", {\n      description: `${eventType} event created for ${selectedDate?.toLocaleDateString()} at ${venue}`,\n    })\n  }\n\n  return (\n    <div className=\"not-prose mx-auto max-w-[530px] p-8\">\n      <div className=\"mb-8 text-center\">\n        <h1 className=\"mb-2 text-3xl font-semibold tracking-tight\">\n          Create Your Event\n        </h1>\n        <p className=\"text-balance text-muted-foreground\">\n          Fill out the form below to create and customize your upcoming event\n        </p>\n      </div>\n\n      <form className=\"space-y-8\" onSubmit={handleSubmit}>\n        {/* Basic Information */}\n        <div className=\"space-y-4\">\n          <h2 className=\"flex items-center gap-2 text-xl font-semibold\">\n            <InfoIcon className=\"size-5\" />\n            Basic Information\n          </h2>\n          <div className=\"grid gap-4 md:grid-cols-2\">\n            <div className=\"space-y-2\">\n              <Label htmlFor=\"event-name\">Event Name</Label>\n              <Input\n                id=\"event-name\"\n                placeholder=\"Enter your event name\"\n                required\n              />\n            </div>\n            <div className=\"space-y-2\">\n              <Label htmlFor=\"organizer\">Organizer</Label>\n              <Input\n                id=\"organizer\"\n                placeholder=\"Your name or organization\"\n                required\n              />\n            </div>\n          </div>\n          <div className=\"space-y-2\">\n            <Label htmlFor=\"description\">Description</Label>\n            <Textarea\n              id=\"description\"\n              placeholder=\"Describe your event in detail...\"\n              rows={3}\n            />\n          </div>\n        </div>\n\n        {/* Event Type Selection */}\n        <div className=\"space-y-4\">\n          <h2 className=\"flex items-center gap-2 text-xl font-semibold\">\n            <UsersIcon className=\"size-5\" />\n            Event Type\n          </h2>\n          <Choicebox onValueChange={setEventType} value={eventType}>\n            {eventTypes.map((type) => (\n              <ChoiceboxItem key={type.value} value={type.value}>\n                <ChoiceboxItemHeader>\n                  <ChoiceboxItemTitle>{type.label}</ChoiceboxItemTitle>\n                  <ChoiceboxItemDescription>\n                    {type.description}\n                  </ChoiceboxItemDescription>\n                </ChoiceboxItemHeader>\n                <ChoiceboxIndicator />\n              </ChoiceboxItem>\n            ))}\n          </Choicebox>\n        </div>\n\n        {/* Venue Selection */}\n        <div className=\"space-y-4\">\n          <h2 className=\"flex items-center gap-2 text-xl font-semibold\">\n            <MapPinIcon className=\"size-5\" />\n            Venue\n          </h2>\n          <Combobox\n            data={venues}\n            onValueChange={setVenue}\n            type=\"venue\"\n            value={venue}\n          >\n            <ComboboxTrigger className=\"w-full\" />\n            <ComboboxContent>\n              <ComboboxInput />\n              <ComboboxList>\n                <ComboboxEmpty />\n                <ComboboxGroup>\n                  {venues.map((venue) => (\n                    <ComboboxItem key={venue.value} value={venue.value}>\n                      {venue.label}\n                    </ComboboxItem>\n                  ))}\n                </ComboboxGroup>\n              </ComboboxList>\n            </ComboboxContent>\n          </Combobox>\n        </div>\n\n        {/* Date Selection */}\n        <div className=\"space-y-4\">\n          <h2 className=\"flex items-center gap-2 text-xl font-semibold\">\n            <CalendarIcon className=\"size-5\" />\n            Select Date\n          </h2>\n          <MiniCalendar\n            className=\"w-fit\"\n            days={7}\n            onValueChange={setSelectedDate}\n            value={selectedDate}\n          >\n            <MiniCalendarNavigation direction=\"prev\" />\n            <MiniCalendarDays>\n              {(date) => (\n                <MiniCalendarDay date={date} key={date.toISOString()} />\n              )}\n            </MiniCalendarDays>\n            <MiniCalendarNavigation direction=\"next\" />\n          </MiniCalendar>\n        </div>\n\n        {/* Tags Selection */}\n        <div className=\"space-y-4\">\n          <h2 className=\"flex items-center gap-2 text-xl font-semibold\">\n            <TagIcon className=\"size-5\" />\n            Event Tags\n          </h2>\n          <Tags>\n            <TagsTrigger>\n              {selectedTags.map((tag) => (\n                <TagsValue key={tag} onRemove={() => handleTagRemove(tag)}>\n                  {tag}\n                </TagsValue>\n              ))}\n            </TagsTrigger>\n            <TagsContent>\n              <TagsInput placeholder=\"Search tags...\" />\n              <TagsList>\n                <TagsEmpty>No tags found.</TagsEmpty>\n                <TagsGroup>\n                  {availableTags\n                    .filter((tag) => !selectedTags.includes(tag))\n                    .map((tag) => (\n                      <TagsItem key={tag} onSelect={() => handleTagSelect(tag)}>\n                        {tag}\n                      </TagsItem>\n                    ))}\n                </TagsGroup>\n              </TagsList>\n            </TagsContent>\n          </Tags>\n        </div>\n\n        {/* File Upload */}\n        <div className=\"space-y-4\">\n          <h2 className=\"flex items-center gap-2 text-xl font-semibold\">\n            <ImageIcon className=\"size-5\" />\n            Event Images\n          </h2>\n          <Dropzone\n            accept={{\n              \"image/*\": [\".png\", \".jpg\", \".jpeg\", \".gif\", \".webp\"],\n            }}\n            maxFiles={5}\n            maxSize={5 * 1024 * 1024} // 5MB\n            onDrop={(acceptedFiles) => setFiles(acceptedFiles)}\n          >\n            <DropzoneEmptyState />\n            <DropzoneContent />\n          </Dropzone>\n          {files.length > 0 && (\n            <div className=\"text-sm text-muted-foreground\">\n              {files.length} file{files.length > 1 ? \"s\" : \"\"} selected\n            </div>\n          )}\n        </div>\n\n        {/* Submit Button */}\n        <div className=\"flex justify-end space-x-4\">\n          <Button type=\"button\" variant=\"outline\">\n            Save as Draft\n          </Button>\n          <Button type=\"submit\">Create Event</Button>\n        </div>\n      </form>\n    </div>\n  )\n}\n\nexport default Example\n",
      "type": "registry:example"
    }
  ],
  "categories": [
    "blocks",
    "form"
  ],
  "type": "registry:example"
}