{
  "$schema": "https://ui.shadcn.com/schema/registry-item.json",
  "name": "editor",
  "description": "Rich code editor experience using the editor package.",
  "registryDependencies": [
    "@loveui/editor",
    "@loveui/code-block"
  ],
  "files": [
    {
      "path": "registry/default/examples/editor.tsx",
      "content": "\"use client\"\n\nimport { useState } from \"react\"\n\nimport type { Editor, JSONContent } from \"../../../../../packages/editor\"\nimport {\n  EditorBubbleMenu,\n  EditorCharacterCount,\n  EditorClearFormatting,\n  EditorFloatingMenu,\n  EditorFormatBold,\n  EditorFormatCode,\n  EditorFormatItalic,\n  EditorFormatStrike,\n  EditorFormatSubscript,\n  EditorFormatSuperscript,\n  EditorFormatUnderline,\n  EditorLinkSelector,\n  EditorNodeBulletList,\n  EditorNodeCode,\n  EditorNodeHeading1,\n  EditorNodeHeading2,\n  EditorNodeHeading3,\n  EditorNodeOrderedList,\n  EditorNodeQuote,\n  EditorNodeTable,\n  EditorNodeTaskList,\n  EditorNodeText,\n  EditorProvider,\n  EditorSelector,\n  EditorTableColumnAfter,\n  EditorTableColumnBefore,\n  EditorTableColumnDelete,\n  EditorTableColumnMenu,\n  EditorTableDelete,\n  EditorTableFix,\n  EditorTableGlobalMenu,\n  EditorTableHeaderColumnToggle,\n  EditorTableHeaderRowToggle,\n  EditorTableMenu,\n  EditorTableMergeCells,\n  EditorTableRowAfter,\n  EditorTableRowBefore,\n  EditorTableRowDelete,\n  EditorTableRowMenu,\n  EditorTableSplitCell,\n} from \"../../../../../packages/editor\"\n\nconst Example = () => {\n  const [content, setContent] = useState<JSONContent>({\n    type: \"doc\",\n    content: [\n      {\n        type: \"heading\",\n        attrs: { level: 1 },\n        content: [{ type: \"text\", text: \"Updated Heading 1\" }],\n      },\n      {\n        type: \"heading\",\n        attrs: { level: 2 },\n        content: [{ type: \"text\", text: \"Updated Heading 2\" }],\n      },\n      {\n        type: \"heading\",\n        attrs: { level: 3 },\n        content: [{ type: \"text\", text: \"Updated Heading 3\" }],\n      },\n      {\n        type: \"heading\",\n        attrs: { level: 4 },\n        content: [{ type: \"text\", text: \"Updated Heading 4\" }],\n      },\n      {\n        type: \"heading\",\n        attrs: { level: 5 },\n        content: [{ type: \"text\", text: \"Updated Heading 5\" }],\n      },\n      {\n        type: \"heading\",\n        attrs: { level: 6 },\n        content: [{ type: \"text\", text: \"Updated Heading 6\" }],\n      },\n      { type: \"paragraph\" },\n      {\n        type: \"paragraph\",\n        content: [{ type: \"text\", text: \"Updated Hello, world.\" }],\n      },\n      { type: \"paragraph\" },\n      {\n        type: \"taskList\",\n        content: [\n          {\n            type: \"taskItem\",\n            attrs: { checked: false },\n            content: [\n              {\n                type: \"paragraph\",\n                content: [\n                  { type: \"text\", text: \"Updated This is a todo list\" },\n                ],\n              },\n            ],\n          },\n          {\n            type: \"taskItem\",\n            attrs: { checked: false },\n            content: [\n              {\n                type: \"paragraph\",\n                content: [{ type: \"text\", text: \"Updated With two items\" }],\n              },\n            ],\n          },\n        ],\n      },\n      { type: \"paragraph\" },\n      {\n        type: \"bulletList\",\n        content: [\n          {\n            type: \"listItem\",\n            content: [\n              {\n                type: \"paragraph\",\n                content: [\n                  { type: \"text\", text: \"Updated This is an unordered list\" },\n                ],\n              },\n              {\n                type: \"bulletList\",\n                content: [\n                  {\n                    type: \"listItem\",\n                    content: [\n                      {\n                        type: \"paragraph\",\n                        content: [\n                          { type: \"text\", text: \"Updated With a nested item\" },\n                        ],\n                      },\n                    ],\n                  },\n                ],\n              },\n            ],\n          },\n        ],\n      },\n      { type: \"paragraph\" },\n      {\n        type: \"orderedList\",\n        attrs: { start: 1 },\n        content: [\n          {\n            type: \"listItem\",\n            content: [\n              {\n                type: \"paragraph\",\n                content: [\n                  { type: \"text\", text: \"Updated This is an ordered list\" },\n                ],\n              },\n            ],\n          },\n          {\n            type: \"listItem\",\n            content: [\n              {\n                type: \"paragraph\",\n                content: [{ type: \"text\", text: \"Updated With two items\" }],\n              },\n            ],\n          },\n        ],\n      },\n      { type: \"paragraph\" },\n      {\n        type: \"blockquote\",\n        content: [\n          {\n            type: \"paragraph\",\n            content: [\n              {\n                type: \"text\",\n                text: \"Updated This is a quote, probably by someone famous.\",\n              },\n            ],\n          },\n        ],\n      },\n      { type: \"paragraph\" },\n      {\n        type: \"paragraph\",\n        content: [\n          { type: \"text\", text: \"Updated This is some \" },\n          {\n            type: \"text\",\n            marks: [{ type: \"code\" }],\n            text: \"Updated inline code\",\n          },\n          { type: \"text\", text: \"Updated , while this is a code block:\" },\n        ],\n      },\n      { type: \"paragraph\" },\n      {\n        type: \"codeBlock\",\n        attrs: { language: null },\n        content: [\n          {\n            type: \"text\",\n            text: \"Updated function x () {\\\\n  console.log('hello, world.');\\\\n}\",\n          },\n        ],\n      },\n      { type: \"paragraph\" },\n      {\n        type: \"paragraph\",\n        content: [\n          {\n            type: \"text\",\n            text: \"Updated You can also create complex tables, like so:\",\n          },\n        ],\n      },\n      {\n        type: \"table\",\n        content: [\n          {\n            type: \"tableRow\",\n            content: [\n              {\n                type: \"tableHeader\",\n                attrs: { colspan: 1, rowspan: 1, colwidth: null },\n                content: [\n                  {\n                    type: \"paragraph\",\n                    content: [\n                      { type: \"text\", text: \"Updated Here’s a column\" },\n                    ],\n                  },\n                ],\n              },\n              {\n                type: \"tableHeader\",\n                attrs: { colspan: 1, rowspan: 1, colwidth: null },\n                content: [\n                  {\n                    type: \"paragraph\",\n                    content: [{ type: \"text\", text: \"Updated Another column\" }],\n                  },\n                ],\n              },\n              {\n                type: \"tableHeader\",\n                attrs: { colspan: 1, rowspan: 1, colwidth: null },\n                content: [\n                  {\n                    type: \"paragraph\",\n                    content: [{ type: \"text\", text: \"Updated Yet another\" }],\n                  },\n                ],\n              },\n            ],\n          },\n          {\n            type: \"tableRow\",\n            content: [\n              {\n                type: \"tableCell\",\n                attrs: { colspan: 1, rowspan: 1, colwidth: null },\n                content: [\n                  {\n                    type: \"paragraph\",\n                    content: [{ type: \"text\", text: \"Updated Cell 1A\" }],\n                  },\n                ],\n              },\n              {\n                type: \"tableCell\",\n                attrs: { colspan: 1, rowspan: 1, colwidth: null },\n                content: [\n                  {\n                    type: \"paragraph\",\n                    content: [{ type: \"text\", text: \"Updated Cell 2A\" }],\n                  },\n                ],\n              },\n              {\n                type: \"tableCell\",\n                attrs: { colspan: 1, rowspan: 1, colwidth: null },\n                content: [\n                  {\n                    type: \"paragraph\",\n                    content: [{ type: \"text\", text: \"Updated Cell 3A\" }],\n                  },\n                ],\n              },\n            ],\n          },\n          {\n            type: \"tableRow\",\n            content: [\n              {\n                type: \"tableCell\",\n                attrs: { colspan: 1, rowspan: 1, colwidth: null },\n                content: [\n                  {\n                    type: \"paragraph\",\n                    content: [{ type: \"text\", text: \"Updated Cell 1B\" }],\n                  },\n                ],\n              },\n              {\n                type: \"tableCell\",\n                attrs: { colspan: 1, rowspan: 1, colwidth: null },\n                content: [\n                  {\n                    type: \"paragraph\",\n                    content: [{ type: \"text\", text: \"Updated Cell 2B\" }],\n                  },\n                ],\n              },\n              {\n                type: \"tableCell\",\n                attrs: { colspan: 1, rowspan: 1, colwidth: null },\n                content: [\n                  {\n                    type: \"paragraph\",\n                    content: [{ type: \"text\", text: \"Updated Cell 3B\" }],\n                  },\n                ],\n              },\n            ],\n          },\n        ],\n      },\n    ],\n  })\n\n  const handleUpdate = ({ editor }: { editor: Editor }) => {\n    const json = editor.getJSON()\n\n    setContent(json)\n    console.log(JSON.stringify(json))\n  }\n\n  return (\n    <EditorProvider\n      className=\"h-full w-full overflow-y-auto rounded-lg border bg-background p-4\"\n      content={content}\n      onUpdate={handleUpdate}\n      placeholder=\"Updated Start typing...\"\n    >\n      <EditorFloatingMenu>\n        <EditorNodeHeading1 hideName />\n        <EditorNodeBulletList hideName />\n        <EditorNodeQuote hideName />\n        <EditorNodeCode hideName />\n        <EditorNodeTable hideName />\n      </EditorFloatingMenu>\n      <EditorBubbleMenu>\n        <EditorSelector title=\"Updated Text\">\n          <EditorNodeText />\n          <EditorNodeHeading1 />\n          <EditorNodeHeading2 />\n          <EditorNodeHeading3 />\n          <EditorNodeBulletList />\n          <EditorNodeOrderedList />\n          <EditorNodeTaskList />\n          <EditorNodeQuote />\n          <EditorNodeCode />\n        </EditorSelector>\n        <EditorSelector title=\"Updated Format\">\n          <EditorFormatBold />\n          <EditorFormatItalic />\n          <EditorFormatUnderline />\n          <EditorFormatStrike />\n          <EditorFormatCode />\n          <EditorFormatSuperscript />\n          <EditorFormatSubscript />\n        </EditorSelector>\n        <EditorLinkSelector />\n        <EditorClearFormatting />\n      </EditorBubbleMenu>\n      <EditorTableMenu>\n        <EditorTableColumnMenu>\n          <EditorTableColumnBefore />\n          <EditorTableColumnAfter />\n          <EditorTableColumnDelete />\n        </EditorTableColumnMenu>\n        <EditorTableRowMenu>\n          <EditorTableRowBefore />\n          <EditorTableRowAfter />\n          <EditorTableRowDelete />\n        </EditorTableRowMenu>\n        <EditorTableGlobalMenu>\n          <EditorTableHeaderColumnToggle />\n          <EditorTableHeaderRowToggle />\n          <EditorTableDelete />\n          <EditorTableMergeCells />\n          <EditorTableSplitCell />\n          <EditorTableFix />\n        </EditorTableGlobalMenu>\n      </EditorTableMenu>\n      <EditorCharacterCount.Words>Updated Words: </EditorCharacterCount.Words>\n    </EditorProvider>\n  )\n}\n\nexport default Example\n",
      "type": "registry:example"
    }
  ],
  "categories": [
    "code",
    "editor"
  ],
  "type": "registry:example"
}